pyrpmdb/__init__.py
pyrpmdb/_pyrpmdb.cpython-311-aarch64-linux-gnu.h
pyrpmdb/_pyrpmdb.cpython-311-aarch64-linux-gnu.so
pyrpmdb/_pyinstaller/__init__.py
pyrpmdb/_pyinstaller/hook-pyrpmdb.py
pyrpmdb-0.1.29.data/scripts/get_rpm_info
pyrpmdb-0.1.29.dist-info/METADATA
pyrpmdb-0.1.29.dist-info/WHEEL
pyrpmdb-0.1.29.dist-info/entry_points.txt
pyrpmdb-0.1.29.dist-info/top_level.txt
pyrpmdb-0.1.29.dist-info/RECORD
pyrpmdb-0.1.29.dist-info/licenses/LICENSE
