Metadata-Version: 2.4
Name: pyrpmdb
Version: 0.1.29
Summary: A utility to extract rpm package information from rpm database
Home-page: https://github.com/Mikemoore63/pyrpmdb
Author: Mike Moore
Author-email: z_z_zebra@yahoo.com
License: MIT
Classifier: Programming Language :: Python :: 3
Classifier: License :: OSI Approved :: MIT License
Classifier: Operating System :: OS Independent
License-File: LICENSE
Dynamic: license-file
